streamlit_pagination_component/__init__.py
streamlit_pagination_component/frontend/build/asset-manifest.json
streamlit_pagination_component/frontend/build/bootstrap.min.css
streamlit_pagination_component/frontend/build/bootstrap.min.css.map
streamlit_pagination_component/frontend/build/index.html
streamlit_pagination_component/frontend/build/precache-manifest.991a64e3b2d72a6ec4048cbdc37353a0.js
streamlit_pagination_component/frontend/build/precache-manifest.99b77391370fc43f9db7ab61a7f3c277.js
streamlit_pagination_component/frontend/build/service-worker.js
streamlit_pagination_component/frontend/build/static/js/2.2329100f.chunk.js
streamlit_pagination_component/frontend/build/static/js/2.2329100f.chunk.js.LICENSE.txt
streamlit_pagination_component/frontend/build/static/js/2.2329100f.chunk.js.map
streamlit_pagination_component/frontend/build/static/js/main.f3cd64ef.chunk.js
streamlit_pagination_component/frontend/build/static/js/main.f3cd64ef.chunk.js.map
streamlit_pagination_component/frontend/build/static/js/main.fd6452e5.chunk.js
streamlit_pagination_component/frontend/build/static/js/main.fd6452e5.chunk.js.map
streamlit_pagination_component/frontend/build/static/js/runtime-main.af1ee0c6.js
streamlit_pagination_component/frontend/build/static/js/runtime-main.af1ee0c6.js.map
streamlit_pagination_component-0.0.4.dist-info/LICENSE
streamlit_pagination_component-0.0.4.dist-info/METADATA
streamlit_pagination_component-0.0.4.dist-info/WHEEL
streamlit_pagination_component-0.0.4.dist-info/top_level.txt
streamlit_pagination_component-0.0.4.dist-info/RECORD
